[{"name":"Clusters Survey#44","amount":1,"options":["Test option delete 1","Test option delete 2","Test option delete 3"],"children":[{"name":"Cluster 1","midpoint":[1,2,0],"like":[0,0,0],"dislike":[0,0,0],"far":0,"fardist":0,"children":[{"name":"Cody@enodo.com","num":"ee022040-807f-49e3-89d7-cdfe849937c0","Genderid":1,"Gender":"Male","Demographic":"Caucasion","Demographicid":5,"Country":"USA","numanswers":[1,2,0],"stringans":["Test option delete 2","Test option delete 3","Test option delete 1"]}]}]}]